dumpscan/__init__.py
dumpscan/common/__init__.py
dumpscan/common/output.py
dumpscan/common/rules.py
dumpscan/common/scanners/__init__.py
dumpscan/common/scanners/symcrypt.py
dumpscan/common/scanners/x509.py
dumpscan/common/structs.py
dumpscan/kernel/__init__.py
dumpscan/kernel/filehandler.py
dumpscan/kernel/plugins/__init__.py
dumpscan/kernel/plugins/dumpcerts.py
dumpscan/kernel/plugins/symcrypt.py
dumpscan/kernel/renderers.py
dumpscan/kernel/vol.py
dumpscan/main.py
dumpscan/minidump/__init__.py
dumpscan/minidump/constants.py
dumpscan/minidump/minidumpfile.py
dumpscan/minidump/structs/__init__.py
dumpscan/minidump/structs/common.py
dumpscan/minidump/structs/MinidumpDirectory.py
dumpscan/minidump/structs/MinidumpHeader.py
dumpscan/minidump/structs/MinidumpMemory64List.py
dumpscan/minidump/structs/MinidumpMemoryList.py
dumpscan/minidump/structs/MinidumpThreadList.py
dumpscan-0.1.1.dist-info/entry_points.txt
dumpscan-0.1.1.dist-info/LICENSE
dumpscan-0.1.1.dist-info/WHEEL
dumpscan-0.1.1.dist-info/METADATA
dumpscan-0.1.1.dist-info/RECORD
