Metadata-Version: 2.1
Name: dumpscan
Version: 0.1.1
Summary: Scanning memory dumps for secrets using volatility and yara
License: MIT
Author: Leron Gray
Author-email: daddycocoaman@gmail.com
Requires-Python: >=3.9,<4.0
Classifier: License :: OSI Approved :: MIT License
Classifier: Programming Language :: Python :: 3
Classifier: Programming Language :: Python :: 3.9
Classifier: Programming Language :: Python :: 3.10
Requires-Dist: arrow (>=1.2.2,<2.0.0)
Requires-Dist: capstone (>=5.0.0rc2,<6.0.0)
Requires-Dist: cffi (>=1.15.0,<2.0.0)
Requires-Dist: construct (>=2.10.68,<3.0.0)
Requires-Dist: cryptography (>=37.0.2,<38.0.0)
Requires-Dist: jsonschema (>=4.5.1,<5.0.0)
Requires-Dist: pefile (>=2022.5.30,<2023.0.0)
Requires-Dist: pycryptodome (>=3.14.1,<4.0.0)
Requires-Dist: rich (>=12.3.0,<13.0.0)
Requires-Dist: rich-click[typer] (>=1.4,<2.0)
Requires-Dist: typer (>=0.4.1,<0.5.0)
Requires-Dist: yara-python (>=3.8.0)
